README.md
setup.py
ultimatelabeling/__init__.py
ultimatelabeling/class_names.py
ultimatelabeling/config.py
ultimatelabeling/main.py
ultimatelabeling/utils.py
ultimatelabeling.egg-info/PKG-INFO
ultimatelabeling.egg-info/SOURCES.txt
ultimatelabeling.egg-info/dependency_links.txt
ultimatelabeling.egg-info/requires.txt
ultimatelabeling.egg-info/top_level.txt
ultimatelabeling/models/__init__.py
ultimatelabeling/models/detector.py
ultimatelabeling/models/hungarian_tracker.py
ultimatelabeling/models/keyboard_listener.py
ultimatelabeling/models/polygon.py
ultimatelabeling/models/ssh_credentials.py
ultimatelabeling/models/state.py
ultimatelabeling/models/track_info.py
ultimatelabeling/models/tracker.py
ultimatelabeling/siamMask/__init__.py
ultimatelabeling/siamMask/test.py
ultimatelabeling/siamMask/models/__init__.py
ultimatelabeling/siamMask/models/custom.py
ultimatelabeling/siamMask/models/features.py
ultimatelabeling/siamMask/models/mask.py
ultimatelabeling/siamMask/models/resnet.py
ultimatelabeling/siamMask/models/rpn.py
ultimatelabeling/siamMask/models/siammask.py
ultimatelabeling/siamMask/utils/__init__.py
ultimatelabeling/siamMask/utils/anchors.py
ultimatelabeling/siamMask/utils/bbox_helper.py
ultimatelabeling/siamMask/utils/benchmark_helper.py
ultimatelabeling/siamMask/utils/config_helper.py
ultimatelabeling/siamMask/utils/load_helper.py
ultimatelabeling/siamMask/utils/log_helper.py
ultimatelabeling/siamMask/utils/tracker_config.py
ultimatelabeling/styles/__init__.py
ultimatelabeling/styles/palettes.py
ultimatelabeling/styles/theme.py
ultimatelabeling/views/__init__.py
ultimatelabeling/views/detection_manager.py
ultimatelabeling/views/hungarian_manager.py
ultimatelabeling/views/image_viewer.py
ultimatelabeling/views/info_detection.py
ultimatelabeling/views/message_progress.py
ultimatelabeling/views/player.py
ultimatelabeling/views/slider.py
ultimatelabeling/views/ssh_login.py
ultimatelabeling/views/theme_picker.py
ultimatelabeling/views/tracking_manager.py
ultimatelabeling/views/video_list.py