Metadata-Version: 2.1
Name: ultimatelabeling
Version: 0.1.1
Summary: A multi-purpose Video Labeling GUI in Python with integrated SOTA detector and tracker.
Home-page: https://github.com/alexandre01/UltimateLabeling
Author: Alexandre Carlier
Author-email: alexandre.carlier01@gmail.com
License: MIT
Platform: UNKNOWN
Classifier: Programming Language :: Python
Classifier: Programming Language :: Python :: 3.7
Provides-Extra: test
